{
  "/plans/36334": "너겟49 월 120GB + 5Mbps 통화 무제한 문자 무제한 LG U+망 5G 혜택가 6개월간 월 12,000원 월 49,000원",
  "/plans/36263": "[일반] 유심 5G 150GB+_24개월 월 150GB + 5Mbps 통화 무제한 문자 무제한 LG U+망 5G 월 26,500원 24개월 이후 56,100원",
  "/plans/36990": "[모요only] 5G_신한카드_기본125G안심5 월 125GB + 5Mbps 통화 무제한 문자 무제한 LG U+망 5G 월 23,700원 24개월 이후 57,200원",
  "/plans/36606": "5G_모나기본150G안심5 월 150GB + 5Mbps 통화 무제한 문자 무제한 LG U+망 5G 월 25,600원 24개월 이후 62,700원",
  "/plans/34816": "음성기본 매일 5GB+_24개월 매일 5GB + 5Mbps 통화 무제한 문자 무제한 LG U+망 LTE 월 27,900원 24개월 이후 47,300원",
  "/plans/30912": "이지 더 오래쓰는 무제한 11G+3 월 11GB + 매일 2GB + 3Mbps 통화 무제한 문자 무제한 LG U+망 LTE 월 25,410원 24개월 이후 39,600원",
  "/plans/20100": "[일반] 통화, 데이터 마음대로 Pro_24개월 매일 5GB + 5Mbps 통화 무제한 문자 무제한 LG U+망 LTE 월 27,900원 24개월 이후 47,300원",
  "/plans/24033": "5G 음성기본 95GB+3Mbps_24개월 월 95GB + 3Mbps 통화 무제한 문자 무제한 LG U+망 5G 월 25,000원 24개월 이후 48,400원",
  "/plans/20101": "[일반] 통화, 데이터 마음대로 11GB+_24개월 월 11GB + 매일 2GB + 3Mbps 통화 무제한 문자 무제한 LG U+망 LTE 월 25,200원 24개월 이후 41,800원",
  "/plans/36690": "[일반] 유심 5G 125GB+_24개월 월 125GB + 5Mbps 통화 무제한 문자 무제한 LG U+망 5G 월 25,500원 24개월 이후 51,150원",
  "/plans/27743": "[일반] 통화, 데이터 마음대로 100GB+_24개월 월 100GB + 5Mbps 통화 무제한 문자 무제한 LG U+망 LTE 월 27,900원 24개월 이후 47,300원",
  "/plans/26357": "[평생할인] 통화, 데이터 마음대로 11GB+ 월 11GB + 매일 2GB + 3Mbps 통화 무제한 문자 무제한 LG U+망 LTE 월 27,900원",
  "/plans/36991": "[모요only] 5G_신한카드_기본150G안심5 월 150GB + 5Mbps 통화 무제한 문자 무제한 LG U+망 5G 월 24,900원 24개월 이후 62,700원",
  "/plans/23406": "NA알뜰11G+일2G+3Mbps 월 11GB + 매일 2GB + 3Mbps 통화 무제한 문자 무제한 LG U+망 LTE 월 25,600원 24개월 이후 39,600원",
  "/plans/30913": "이지 더 오래쓰는 무제한 100G+5 월 100GB + 5Mbps 통화 무제한 문자 무제한 LG U+망 LTE 월 28,380원 24개월 이후 46,200원",
  "/plans/36605": "5G_모나기본125G안심5 월 125GB + 5Mbps 통화 무제한 문자 무제한 LG U+망 5G 월 24,860원 24개월 이후 57,200원",
  "/plans/34879": "두해 통화기본11GB+매일2GB 월 11GB + 매일 2GB + 3Mbps 통화 무제한 문자 무제한 LG U+망 LTE 월 24,210원 24개월 이후 39,610원",
  "/plans/34808": "음성기본 11GB+일 2GB+_24개월 월 11GB + 매일 2GB + 3Mbps 통화 무제한 문자 무제한 LG U+망 LTE 월 24,700원 24개월 이후 38,500원",
  "/plans/27454": "Sugar 통화마음대로 11GB+매일2GB+ 월 11GB + 매일 2GB + 3Mbps 통화 무제한 문자 무제한 LG U+망 LTE 월 25,900원 24개월 이후 39,000원",
  "/plans/34881": "두해 통화기본100GB+ 월 100GB + 5Mbps 통화 무제한 문자 무제한 LG U+망 LTE 월 27,990원 24개월 이후 47,350원",
  "/plans/36691": "[일반] 유심 5G 95GB+_24개월 월 95GB + 3Mbps 통화 무제한 문자 무제한 LG U+망 5G 월 25,400원 24개월 이후 49,500원",
  "/plans/36688": "[평생할인] 유심 5G 125GB+ 월 125GB + 5Mbps 통화 무제한 문자 무제한 LG U+망 5G 월 29,600원",
  "/plans/33623": "이야기스페셜 100GB+(24개월) 월 100GB + 5Mbps 통화 무제한 문자 무제한 LG U+망 LTE 월 28,500원 24개월 이후 46,200원",
  "/plans/23124": "5G Sugar 통화마음대로 95GB+ 월 95GB + 3Mbps 통화 무제한 문자 무제한 LG U+망 5G 월 27,900원 24개월 이후 45,500원",
  "/plans/23408": "NA알뜰매일5GB+5Mbps 매일 5GB + 5Mbps 통화 무제한 문자 무제한 LG U+망 LTE 월 28,600원 24개월 이후 46,200원",
  "/plans/23170": "5G Sugar 통화마음대로 125GB++ 월 125GB + 5Mbps 통화 무제한 문자 무제한 LG U+망 5G 월 28,900원 24개월 이후 47,000원",
  "/plans/35525": "5G_LOCAL_기본95G안심3 월 95GB + 3Mbps 통화 무제한 문자 무제한 LG U+망 5G 월 25,200원 24개월 이후 55,000원",
  "/plans/30914": "이지 더 오래쓰는 무제한 일5G+5 매일 5GB + 5Mbps 통화 무제한 문자 무제한 LG U+망 LTE 월 28,380원 24개월 이후 46,200원",
  "/plans/36164": "코나아이데이터11G+일2G 월 11GB + 매일 2GB + 3Mbps 통화 무제한 문자 무제한 LG U+망 LTE 월 27,600원",
  "/plans/27745": "모나기본100G안심5 월 100GB + 5Mbps 통화 무제한 문자 무제한 LG U+망 LTE 월 28,600원 24개월 이후 48,400원",
  "/plans/34880": "두해 통화기본매일5GB+ 매일 5GB + 5Mbps 통화 무제한 문자 무제한 LG U+망 LTE 월 27,990원 24개월 이후 46,250원",
  "/plans/28097": "스마트 11GB+ (24개월) 월 11GB + 매일 2GB + 3Mbps 통화 무제한 문자 무제한 LG U+망 LTE 월 27,000원 24개월 이후 40,700원",
  "/plans/23171": "5G Sugar 통화마음대로 150GB++ 월 150GB + 5Mbps 통화 무제한 문자 무제한 LG U+망 5G 월 29,900원 24개월 이후 50,700원",
  "/plans/27453": "Sugar 데이터안심 매일5GB++ 매일 5GB + 5Mbps 통화 무제한 문자 무제한 LG U+망 LTE 월 29,900원 24개월 이후 49,000원",
  "/plans/36689": "[평생할인] 유심 5G 95GB+ 월 95GB + 3Mbps 통화 무제한 문자 무제한 LG U+망 5G 월 29,300원",
  "/plans/35523": "편의점_데이터11G+일2G 월 11GB + 매일 2GB + 3Mbps 통화 무제한 문자 무제한 LG U+망 LTE 월 27,900원 24개월 이후 44,000원",
  "/plans/23034": "[24개월] 인스 유심 스트롱 11GB+ 월 11GB + 매일 2GB + 3Mbps 통화 무제한 문자 무제한 LG U+망 LTE 월 25,800원 24개월 이후 39,000원",
  "/plans/28098": "스마트 매일 5GB+ (24개월) 매일 5GB + 5Mbps 통화 무제한 문자 무제한 LG U+망 LTE 월 30,000원 24개월 이후 47,300원",
  "/plans/35524": "캐시_데이터11G+일2G 월 11GB + 매일 2GB + 3Mbps 통화 무제한 문자 무제한 LG U+망 LTE 월 28,900원 24개월 이후 44,000원",
  "/plans/28699": "MANIA 통화무제한 100GB++ 월 100GB + 5Mbps 통화 무제한 문자 무제한 LG U+망 LTE 월 29,900원 24개월 이후 50,900원",
  "/plans/23035": "[24개월] 인스 유심 스트롱 매일 5GB+ 매일 5GB + 5Mbps 통화 무제한 문자 무제한 LG U+망 LTE 월 28,520원 24개월 이후 47,000원",
  "/plans/27688": "[24개월] 인스 유심 스트롱 100GB+ 월 100GB + 5Mbps 통화 무제한 문자 무제한 LG U+망 LTE 월 28,520원 24개월 이후 47,000원",
  "/plans/36649": "5G 티플온 150GB+_평생 할인 월 150GB + 5Mbps 통화 무제한 문자 무제한 LG U+망 5G 월 28,400원",
  "/plans/23997": "티플 마음껏 매일5G＋_24개월요금 매일 5GB + 5Mbps 통화 무제한 문자 무제한 LG U+망 LTE 월 27,500원 24개월 이후 41,800원",
  "/plans/14984": "5G 통화 충분 30GB 월 30GB 통화 무제한 문자 무제한 KT망 5G 월 29,900원",
  "/plans/28167": "티플 100G+_평생할인! 월 100GB + 5Mbps 통화 무제한 문자 무제한 LG U+망 LTE 월 28,500원",
  "/plans/35509": "5G 티플온 95GB+_24개월 할인 월 95GB + 3Mbps 통화 무제한 문자 무제한 LG U+망 5G 월 26,900원 24개월 이후 52,800원",
  "/plans/27424": "티플 11G＋_24개월 할인 월 11GB + 매일 2GB + 3Mbps 통화 무제한 문자 무제한 LG U+망 LTE 월 25,500원 24개월 이후 39,600원",
  "/plans/24000": "티플 완전마음껏11G＋_평생요금 월 11GB + 매일 2GB + 3Mbps 통화 무제한 문자 무제한 LG U+망 LTE 월 27,900원",
  "/plans/36986": "[L]5G 데이터150GB+ 월 150GB + 5Mbps 통화 무제한 문자 무제한 LG U+망 5G 월 23,900원 24개월 이후 63,000원",
  "/plans/20326": "함께이야기해S(200분+30GB) 월 30GB 통화 200분 문자 300건 SKT망 LTE 월 23,500원",
  "/plans/13982": "함께이야기해S(500분+30GB) 월 30GB 통화 500분 문자 300건 SKT망 LTE 월 27,500원",
  "/plans/36780": "A 스페셜 매일 5GB+ (24개월) 매일 5GB + 5Mbps 통화 무제한 문자 무제한 LG U+망 LTE 월 24,640원 24개월 이후 47,960원",
  "/plans/36779": "A 스페셜 100GB+ (24개월) 월 100GB + 5Mbps 통화 무제한 문자 무제한 LG U+망 LTE 월 24,640원 24개월 이후 47,960원",
  "/plans/36775": "A 스페셜 11GB+ (24개월) 월 11GB + 매일 2GB + 3Mbps 통화 무제한 문자 무제한 LG U+망 LTE 월 22,440원 24개월 이후 36,300원",
  "/plans/19643": "[L]무한11GB+ 월 11GB + 매일 2GB + 3Mbps 통화 무제한 문자 무제한 LG U+망 LTE 월 25,500원",
  "/plans/36936": "[L] 라운지프리 11GB+ 월 11GB + 매일 2GB + 3Mbps 통화 무제한 문자 무제한 LG U+망 LTE 월 24,000원 24개월 이후 46,000원",
  "/plans/35461": "[S]울트라(300분/30GB) 월 30GB 통화 300분 문자 100건 SKT망 LTE 월 11,900원",
  "/plans/27355": "[L]5G 데이터125GB+5Mbps 월 125GB + 5Mbps 통화 무제한 문자 무제한 LG U+망 5G 월 25,900원 24개월 이후 59,400원",
  "/plans/36938": "[L] 라운지프리 100GB+ 월 100GB + 5Mbps 통화 무제한 문자 무제한 LG U+망 LTE 월 27,000원 24개월 이후 54,000원",
  "/plans/36219": "[L]무한100GB+ 월 100GB + 5Mbps 통화 무제한 문자 무제한 LG U+망 LTE 월 28,500원",
  "/plans/36937": "[L] 데이터11GB+_2y_plus 월 11GB + 매일 2GB + 3Mbps 통화 무제한 문자 무제한 LG U+망 LTE 월 25,500원 24개월 이후 46,000원",
  "/plans/17599": "5G 함께이야기해S (500분+30GB) 월 30GB 통화 500분 문자 200건 SKT망 5G 월 28,600원",
  "/plans/36941": "[L] 데이터 매일5GB+_24개월 매일 5GB + 5Mbps 통화 무제한 문자 무제한 LG U+망 LTE 월 28,500원 24개월 이후 53,900원 10+명이 선택",
  "/plans/36942": "[L] 데이터 100GB+_24개월 월 100GB + 5Mbps 통화 무제한 문자 무제한 LG U+망 LTE 월 28,500원 24개월 이후 53,900원",
  "/plans/16497": "[L]매일5GB+ 매일 5GB + 5Mbps 통화 무제한 문자 무제한 LG U+망 LTE 월 28,500원",
  "/plans/35379": "[S]무한11GB+ 월 11GB + 매일 2GB + 3Mbps 통화 무제한 문자 무제한 SKT망 LTE 월 27,900원",
  "/plans/36939": "[L] 5G 데이터 95GB+_2y_plus 월 95GB + 3Mbps 통화 무제한 문자 무제한 LG U+망 5G 월 27,000원 24개월 이후 55,300원",
  "/plans/36943": "[L] 5G 150GB+ 월 150GB + 5Mbps 통화 무제한 문자 무제한 LG U+망 5G 월 29,000원 24개월 이후 60,500원",
  "/plans/34718": "[L]5G 데이터95GB+3Mbps 월 95GB + 3Mbps 통화 무제한 문자 무제한 LG U+망 5G 월 25,600원 24개월 이후 56,100원",
  "/plans/20054": "청년도약 LTE 71GB+ 월 11GB + 매일 2GB + 3Mbps 통화 무제한 문자 무제한 LG U+망 LTE 월 26,400원 36개월 이후 34,300원",
  "/plans/34891": "더든든한500분30G 월 30GB 통화 500분 문자 100건 SKT망 LTE 월 11,000원",
  "/plans/30443": "프리티데이터중심11G 월 11GB + 매일 2GB + 3Mbps 통화 제공안함 문자 제공안함 LG U+망 LTE 월 26,070원 24개월 이후 39,490원",
  "/plans/30444": "프리티데이터매일5G+ 매일 5GB + 5Mbps 통화 제공안함 문자 제공안함 LG U+망 LTE 월 29,040원 24개월 이후 49,500원",
  "/plans/29769": "LTE 안심차단 (30GB/1000분) 월 30GB 통화 1000분 문자 1000건 SKT망 LTE 월 24,900원"
}